carpetsWebScraper/__init__.py
carpetsWebScraper/carpetsWebScraper.py
carpetsWebScraper-0.0.9.dist-info/METADATA
carpetsWebScraper-0.0.9.dist-info/WHEEL
carpetsWebScraper-0.0.9.dist-info/top_level.txt
carpetsWebScraper-0.0.9.dist-info/RECORD
