Metadata-Version: 2.1
Name: carpetsWebScraper
Version: 0.0.9
Summary: A simplified webscraper that's based on Selenium.
Author: thecarpetjasp
Author-email: thecarpetjasp@gmail.com
Keywords: python,selenium,webscraper
Classifier: Development Status :: 1 - Planning
Classifier: Intended Audience :: Developers
Classifier: Programming Language :: Python :: 3
Classifier: Operating System :: Unix
Classifier: Operating System :: MacOS :: MacOS X
Classifier: Operating System :: Microsoft :: Windows
Requires-Dist: selenium
Requires-Dist: pandas
Requires-Dist: bs4
Requires-Dist: requests
